{
  "trip_key": "PAT-B-2026-06-17",
  "trip_name": "Mi\u00e9\u2192Lun (12 d\u00edas) \u00b7 SCL\u2194GIG 2026-06-17\u21922026-06-29",
  "legs": [
    {
      "origin": "SCL",
      "dest": "GIG",
      "date": "2026-06-17"
    },
    {
      "origin": "GIG",
      "dest": "SCL",
      "date": "2026-06-29"
    }
  ],
  "snapshot_at": "2026-05-27T13:26:53.810743Z",
  "sources": {
    "google_flights": {
      "ok": true,
      "duration_s": 0.0,
      "search_url": "https://www.google.com/travel/flights?tfs=GhwSCjIwMjYtMDYtMTcoAmoFEgNTQ0xyBRIDR0lHGhwSCjIwMjYtMDYtMjkoAmoFEgNHSUdyBRIDU0NMQgEBSAGYAQE=&hl=en&curr=USD",
      "quotes": [
        {
          "legs": [
            {
              "origin": "SCL",
              "dest": "GIG",
              "leg_date": "2026-06-17",
              "airline": "",
              "departure": "",
              "arrival": "",
              "duration_min": 0,
              "stops": 0,
              "price_value": 388925.0,
              "price_currency": "CLP",
              "price_display": "CLP 388925",
              "is_best": true
            }
          ],
          "total_price_value": 388925.0,
          "total_price_currency": "CLP",
          "composition": "round-trip",
          "booking_url": "https://www.google.com/travel/flights?tfs=GhwSCjIwMjYtMDYtMTcoAmoFEgNTQ0xyBRIDR0lHGhwSCjIwMjYtMDYtMjkoAmoFEgNHSUdyBRIDU0NMQgEBSAGYAQE=&hl=en&curr=USD",
          "source": "google_flights",
          "sanity": {
            "suspect": false,
            "reasons": [],
            "distance_km": 2934,
            "min_nonstop_minutes": 245
          }
        },
        {
          "legs": [
            {
              "origin": "SCL",
              "dest": "GIG",
              "leg_date": "2026-06-17",
              "airline": "",
              "departure": "",
              "arrival": "",
              "duration_min": 0,
              "stops": 0,
              "price_value": 388925.0,
              "price_currency": "CLP",
              "price_display": "CLP 388925",
              "is_best": true
            }
          ],
          "total_price_value": 388925.0,
          "total_price_currency": "CLP",
          "composition": "round-trip",
          "booking_url": "https://www.google.com/travel/flights?tfs=GhwSCjIwMjYtMDYtMTcoAmoFEgNTQ0xyBRIDR0lHGhwSCjIwMjYtMDYtMjkoAmoFEgNHSUdyBRIDU0NMQgEBSAGYAQE=&hl=en&curr=USD",
          "source": "google_flights",
          "sanity": {
            "suspect": false,
            "reasons": [],
            "distance_km": 2934,
            "min_nonstop_minutes": 245
          }
        },
        {
          "legs": [
            {
              "origin": "SCL",
              "dest": "GIG",
              "leg_date": "2026-06-17",
              "airline": "",
              "departure": "",
              "arrival": "",
              "duration_min": 0,
              "stops": 0,
              "price_value": 423225.0,
              "price_currency": "CLP",
              "price_display": "CLP 423225",
              "is_best": true
            }
          ],
          "total_price_value": 423225.0,
          "total_price_currency": "CLP",
          "composition": "round-trip",
          "booking_url": "https://www.google.com/travel/flights?tfs=GhwSCjIwMjYtMDYtMTcoAmoFEgNTQ0xyBRIDR0lHGhwSCjIwMjYtMDYtMjkoAmoFEgNHSUdyBRIDU0NMQgEBSAGYAQE=&hl=en&curr=USD",
          "source": "google_flights",
          "sanity": {
            "suspect": false,
            "reasons": [],
            "distance_km": 2934,
            "min_nonstop_minutes": 245
          }
        },
        {
          "legs": [
            {
              "origin": "SCL",
              "dest": "GIG",
              "leg_date": "2026-06-17",
              "airline": "",
              "departure": "",
              "arrival": "",
              "duration_min": 0,
              "stops": 0,
              "price_value": null,
              "price_currency": "USD",
              "price_display": "Check price",
              "is_best": true
            }
          ],
          "total_price_value": null,
          "total_price_currency": "USD",
          "composition": "round-trip",
          "booking_url": "https://www.google.com/travel/flights?tfs=GhwSCjIwMjYtMDYtMTcoAmoFEgNTQ0xyBRIDR0lHGhwSCjIwMjYtMDYtMjkoAmoFEgNHSUdyBRIDU0NMQgEBSAGYAQE=&hl=en&curr=USD",
          "source": "google_flights",
          "sanity": {
            "suspect": false,
            "reasons": [],
            "distance_km": 2934,
            "min_nonstop_minutes": 245
          }
        },
        {
          "legs": [
            {
              "origin": "SCL",
              "dest": "GIG",
              "leg_date": "2026-06-17",
              "airline": "",
              "departure": "",
              "arrival": "",
              "duration_min": 0,
              "stops": 0,
              "price_value": 413531.0,
              "price_currency": "CLP",
              "price_display": "CLP 413531",
              "is_best": false
            }
          ],
          "total_price_value": 413531.0,
          "total_price_currency": "CLP",
          "composition": "round-trip",
          "booking_url": "https://www.google.com/travel/flights?tfs=GhwSCjIwMjYtMDYtMTcoAmoFEgNTQ0xyBRIDR0lHGhwSCjIwMjYtMDYtMjkoAmoFEgNHSUdyBRIDU0NMQgEBSAGYAQE=&hl=en&curr=USD",
          "source": "google_flights",
          "sanity": {
            "suspect": false,
            "reasons": [],
            "distance_km": 2934,
            "min_nonstop_minutes": 245
          }
        }
      ]
    },
    "booking": {
      "ok": true,
      "duration_s": 26.8,
      "search_url": "https://flights.booking.com/flights/SCL.AIRPORT-GIG.AIRPORT/?type=ROUNDTRIP&adults=1&cabinClass=ECONOMY&sort=BEST&from=SCL.AIRPORT&to=GIG.AIRPORT&depart=2026-06-17&return=2026-06-29",
      "quotes": [],
      "note": "no_results_use_link"
    },
    "kayak": {
      "ok": true,
      "duration_s": 8.2,
      "search_url": "https://www.kayak.com/flights/SCL-GIG/2026-06-17/GIG-SCL/2026-06-29?sort=price_a",
      "pack_url": "https://www.kayak.com/flights/SCL-GIG/2026-06-17/GIG-SCL/2026-06-29?sort=price_a",
      "quotes": [
        {
          "legs": [
            {
              "origin": "SCL",
              "dest": "GIG",
              "depart_dt": "2026-06-17",
              "arrive_dt": "",
              "airline": "LATAM",
              "flight_no": "",
              "duration_min": 0
            },
            {
              "origin": "GIG",
              "dest": "SCL",
              "depart_dt": "2026-06-29",
              "arrive_dt": "",
              "airline": "LATAM",
              "flight_no": "",
              "duration_min": 0
            }
          ],
          "price_value": 494.0,
          "price_display": "$494",
          "price_currency": "USD",
          "total_duration_min": 250,
          "n_stops": 0,
          "booking_url": "https://www.kayak.com/flights/SCL-GIG/2026-06-17/GIG-SCL/2026-06-29?sort=price_a",
          "source": "kayak",
          "raw_text": "8:55 pm \u2013 2:05 am+1\nLATAM Airlines\nnonstop\n4h 10m\nSCL\n-\nGIG\n6:30 am \u2013 6:15 pm\nLATAM Airlines\n2 stops\nVIX\n\u00a02h 00m layover, Vit\u00f3ria Eurico Sales\n, GRU\n\u00a03h 40m layover, Sao Paulo Guarulhos Intl\n12h 45m\nGIG\n-\nSCL\n1\n0\n$494\nBasic\nSelect",
          "booking_url_note": "search_link (specific token expired/missing)",
          "sanity": {
            "suspect": false,
            "reasons": [],
            "distance_km": 2934,
            "min_nonstop_minutes": 245
          }
        },
        {
          "legs": [
            {
              "origin": "SCL",
              "dest": "GIG",
              "depart_dt": "2026-06-17",
              "arrive_dt": "",
              "airline": "LATAM",
              "flight_no": "",
              "duration_min": 0
            },
            {
              "origin": "GIG",
              "dest": "SCL",
              "depart_dt": "2026-06-29",
              "arrive_dt": "",
              "airline": "LATAM",
              "flight_no": "",
              "duration_min": 0
            }
          ],
          "price_value": 494.0,
          "price_display": "$494",
          "price_currency": "USD",
          "total_duration_min": 250,
          "n_stops": 0,
          "booking_url": "https://www.kayak.com/flights/SCL-GIG/2026-06-17/GIG-SCL/2026-06-29?sort=price_a",
          "source": "kayak",
          "raw_text": "8:55 pm \u2013 2:05 am+1\nLATAM Airlines\nnonstop\n4h 10m\nSCL\n-\nGIG\n10:15 pm \u2013 10:30 am+1\nLATAM Airlines\n2 stops\nPOA\n\u00a03h 10m layover, Porto Alegre Salgado Filho\n, GRU\n\u00a02h 00m layover, Sao Paulo Guarulhos Intl\n13h 15m\nGIG\n-\nSCL\n1\n0\n$494\nBasic\nSelect",
          "booking_url_note": "search_link (specific token expired/missing)",
          "sanity": {
            "suspect": false,
            "reasons": [],
            "distance_km": 2934,
            "min_nonstop_minutes": 245
          }
        },
        {
          "legs": [
            {
              "origin": "SCL",
              "dest": "GIG",
              "depart_dt": "2026-06-17",
              "arrive_dt": "",
              "airline": "LATAM",
              "flight_no": "",
              "duration_min": 0
            },
            {
              "origin": "GIG",
              "dest": "SCL",
              "depart_dt": "2026-06-29",
              "arrive_dt": "",
              "airline": "LATAM",
              "flight_no": "",
              "duration_min": 0
            }
          ],
          "price_value": 495.0,
          "price_display": "$495",
          "price_currency": "USD",
          "total_duration_min": 205,
          "n_stops": 1,
          "booking_url": "https://www.kayak.com/flights/SCL-GIG/2026-06-17/GIG-SCL/2026-06-29?sort=price_a",
          "source": "kayak",
          "raw_text": "8:30 am \u2013 5:45 pm\nLATAM Airlines\n1 stop\nEZE-AEP\n\u00a03h 25m layover, Airport change EZE-AEP\n8h 15m\nSCL\n-\nGIG\n6:30 am \u2013 6:15 pm\nLATAM Airlines\n2 stops\nVIX\n\u00a02h 00m layover, Vit\u00f3ria Eurico Sales\n, GRU\n\u00a03h 40m layover, Sao Paulo Guarulhos Intl\n12h 45m\nGIG\n-\nSCL\n1\n0\n$495\nBasic\nSelect",
          "booking_url_note": "search_link (specific token expired/missing)",
          "sanity": {
            "suspect": false,
            "reasons": [],
            "distance_km": 2934,
            "min_nonstop_minutes": 245
          }
        },
        {
          "legs": [
            {
              "origin": "SCL",
              "dest": "GIG",
              "depart_dt": "2026-06-17",
              "arrive_dt": "",
              "airline": "LATAM",
              "flight_no": "",
              "duration_min": 0
            },
            {
              "origin": "GIG",
              "dest": "SCL",
              "depart_dt": "2026-06-29",
              "arrive_dt": "",
              "airline": "LATAM",
              "flight_no": "",
              "duration_min": 0
            }
          ],
          "price_value": 495.0,
          "price_display": "$495",
          "price_currency": "USD",
          "total_duration_min": 205,
          "n_stops": 1,
          "booking_url": "https://www.kayak.com/flights/SCL-GIG/2026-06-17/GIG-SCL/2026-06-29?sort=price_a",
          "source": "kayak",
          "raw_text": "8:30 am \u2013 5:45 pm\nLATAM Airlines\n1 stop\nEZE-AEP\n\u00a03h 25m layover, Airport change EZE-AEP\n8h 15m\nSCL\n-\nGIG\n10:15 pm \u2013 10:30 am+1\nLATAM Airlines\n2 stops\nPOA\n\u00a03h 10m layover, Porto Alegre Salgado Filho\n, GRU\n\u00a02h 00m layover, Sao Paulo Guarulhos Intl\n13h 15m\nGIG\n-\nSCL\n1\n0\n$495\nBasic\nSelect",
          "booking_url_note": "search_link (specific token expired/missing)",
          "sanity": {
            "suspect": false,
            "reasons": [],
            "distance_km": 2934,
            "min_nonstop_minutes": 245
          }
        },
        {
          "legs": [
            {
              "origin": "SCL",
              "dest": "GIG",
              "depart_dt": "2026-06-17",
              "arrive_dt": "",
              "airline": "LATAM",
              "flight_no": "",
              "duration_min": 0
            },
            {
              "origin": "GIG",
              "dest": "SCL",
              "depart_dt": "2026-06-29",
              "arrive_dt": "",
              "airline": "LATAM",
              "flight_no": "",
              "duration_min": 0
            }
          ],
          "price_value": 504.0,
          "price_display": "$504",
          "price_currency": "USD",
          "total_duration_min": 90,
          "n_stops": 2,
          "booking_url": "https://www.kayak.com/flights/SCL-GIG/2026-06-17/GIG-SCL/2026-06-29?sort=price_a",
          "source": "kayak",
          "raw_text": "6:00 am \u2013 4:20 pm\nLATAM Airlines\n2 stops\nFLN\n\u00a01h 30m layover, Florianopolis Hercilio Luz\n, GRU\n\u00a02h 05m layover, Sao Paulo Guarulhos Intl\n9h 20m\nSCL\n-\nGIG\n10:15 pm \u2013 10:30 am+1\nLATAM Airlines\n2 stops\nPOA\n\u00a03h 10m layover, Porto Alegre Salgado Filho\n, GRU\n\u00a02h 00m layover, Sao Paulo Guarulhos Intl\n13h 15m\nGIG\n-\nSCL\n1\n0\n$504\nBasic\nSelect",
          "booking_url_note": "search_link (specific token expired/missing)",
          "sanity": {
            "suspect": false,
            "reasons": [],
            "distance_km": 2934,
            "min_nonstop_minutes": 245
          }
        },
        {
          "legs": [
            {
              "origin": "SCL",
              "dest": "GIG",
              "depart_dt": "2026-06-17",
              "arrive_dt": "",
              "airline": "LATAM",
              "flight_no": "",
              "duration_min": 0
            },
            {
              "origin": "GIG",
              "dest": "SCL",
              "depart_dt": "2026-06-29",
              "arrive_dt": "",
              "airline": "LATAM",
              "flight_no": "",
              "duration_min": 0
            }
          ],
          "price_value": 521.0,
          "price_display": "$521",
          "price_currency": "USD",
          "total_duration_min": 250,
          "n_stops": 0,
          "booking_url": "https://www.kayak.com/flights/SCL-GIG/2026-06-17/GIG-SCL/2026-06-29?sort=price_a",
          "source": "kayak",
          "raw_text": "8:55 pm \u2013 2:05 am+1\nLATAM Airlines\nnonstop\n4h 10m\nSCL\n-\nGIG\n4:45 pm \u2013 2:50 am+1\nLATAM Airlines\n2 stops\nPOA\n\u00a01h 05m layover, Porto Alegre Salgado Filho\n, GRU\n\u00a01h 55m layover, Sao Paulo Guarulhos Intl\n11h 05m\nGIG\n-\nSCL\n1\n0\n$521\nBasic\nSelect",
          "booking_url_note": "search_link (specific token expired/missing)",
          "sanity": {
            "suspect": false,
            "reasons": [],
            "distance_km": 2934,
            "min_nonstop_minutes": 245
          }
        },
        {
          "legs": [
            {
              "origin": "SCL",
              "dest": "GIG",
              "depart_dt": "2026-06-17",
              "arrive_dt": "",
              "airline": "LATAM",
              "flight_no": "",
              "duration_min": 0
            },
            {
              "origin": "GIG",
              "dest": "SCL",
              "depart_dt": "2026-06-29",
              "arrive_dt": "",
              "airline": "LATAM",
              "flight_no": "",
              "duration_min": 0
            }
          ],
          "price_value": 521.0,
          "price_display": "$521",
          "price_currency": "USD",
          "total_duration_min": 250,
          "n_stops": 0,
          "booking_url": "https://www.kayak.com/flights/SCL-GIG/2026-06-17/GIG-SCL/2026-06-29?sort=price_a",
          "source": "kayak",
          "raw_text": "8:55 pm \u2013 2:05 am+1\nLATAM Airlines\nnonstop\n4h 10m\nSCL\n-\nGIG\n11:00 am \u2013 9:05 pm\nLATAM Airlines\n2 stops\nPOA\n\u00a01h 10m layover, Porto Alegre Salgado Filho\n, GRU\n\u00a01h 40m layover, Sao Paulo Guarulhos Intl\n11h 05m\nGIG\n-\nSCL\n1\n0\n$521\nBasic\nSelect",
          "booking_url_note": "search_link (specific token expired/missing)",
          "sanity": {
            "suspect": false,
            "reasons": [],
            "distance_km": 2934,
            "min_nonstop_minutes": 245
          }
        },
        {
          "legs": [
            {
              "origin": "SCL",
              "dest": "GIG",
              "depart_dt": "2026-06-17",
              "arrive_dt": "",
              "airline": "LATAM",
              "flight_no": "",
              "duration_min": 0
            },
            {
              "origin": "GIG",
              "dest": "SCL",
              "depart_dt": "2026-06-29",
              "arrive_dt": "",
              "airline": "LATAM",
              "flight_no": "",
              "duration_min": 0
            }
          ],
          "price_value": 522.0,
          "price_display": "$522",
          "price_currency": "USD",
          "total_duration_min": 205,
          "n_stops": 1,
          "booking_url": "https://www.kayak.com/flights/SCL-GIG/2026-06-17/GIG-SCL/2026-06-29?sort=price_a",
          "source": "kayak",
          "raw_text": "8:30 am \u2013 5:45 pm\nLATAM Airlines\n1 stop\nEZE-AEP\n\u00a03h 25m layover, Airport change EZE-AEP\n8h 15m\nSCL\n-\nGIG\n11:00 am \u2013 9:05 pm\nLATAM Airlines\n2 stops\nPOA\n\u00a01h 10m layover, Porto Alegre Salgado Filho\n, GRU\n\u00a01h 40m layover, Sao Paulo Guarulhos Intl\n11h 05m\nGIG\n-\nSCL\n1\n0\n$522\nBasic\nSelect",
          "booking_url_note": "search_link (specific token expired/missing)",
          "sanity": {
            "suspect": false,
            "reasons": [],
            "distance_km": 2934,
            "min_nonstop_minutes": 245
          }
        },
        {
          "legs": [
            {
              "origin": "SCL",
              "dest": "GIG",
              "depart_dt": "2026-06-17",
              "arrive_dt": "",
              "airline": "LATAM",
              "flight_no": "",
              "duration_min": 0
            },
            {
              "origin": "GIG",
              "dest": "SCL",
              "depart_dt": "2026-06-29",
              "arrive_dt": "",
              "airline": "LATAM",
              "flight_no": "",
              "duration_min": 0
            }
          ],
          "price_value": 522.0,
          "price_display": "$522",
          "price_currency": "USD",
          "total_duration_min": 205,
          "n_stops": 1,
          "booking_url": "https://www.kayak.com/flights/SCL-GIG/2026-06-17/GIG-SCL/2026-06-29?sort=price_a",
          "source": "kayak",
          "raw_text": "8:30 am \u2013 5:45 pm\nLATAM Airlines\n1 stop\nEZE-AEP\n\u00a03h 25m layover, Airport change EZE-AEP\n8h 15m\nSCL\n-\nGIG\n4:45 pm \u2013 2:50 am+1\nLATAM Airlines\n2 stops\nPOA\n\u00a01h 05m layover, Porto Alegre Salgado Filho\n, GRU\n\u00a01h 55m layover, Sao Paulo Guarulhos Intl\n11h 05m\nGIG\n-\nSCL\n1\n0\n$522\nBasic\nSelect",
          "booking_url_note": "search_link (specific token expired/missing)",
          "sanity": {
            "suspect": false,
            "reasons": [],
            "distance_km": 2934,
            "min_nonstop_minutes": 245
          }
        },
        {
          "legs": [
            {
              "origin": "SCL",
              "dest": "GIG",
              "depart_dt": "2026-06-17",
              "arrive_dt": "",
              "airline": "LATAM",
              "flight_no": "",
              "duration_min": 0
            },
            {
              "origin": "GIG",
              "dest": "SCL",
              "depart_dt": "2026-06-29",
              "arrive_dt": "",
              "airline": "LATAM",
              "flight_no": "",
              "duration_min": 0
            }
          ],
          "price_value": 544.0,
          "price_display": "$544",
          "price_currency": "USD",
          "total_duration_min": 245,
          "n_stops": 0,
          "booking_url": "https://www.kayak.com/flights/SCL-GIG/2026-06-17/GIG-SCL/2026-06-29?sort=price_a",
          "source": "kayak",
          "raw_text": "12:20 pm \u2013 5:25 pm\nLATAM Airlines\nnonstop\n4h 05m\nSCL\n-\nGIG\n4:45 pm \u2013 2:50 am+1\nLATAM Airlines\n2 stops\nPOA\n\u00a01h 05m layover, Porto Alegre Salgado Filho\n, GRU\n\u00a01h 55m layover, Sao Paulo Guarulhos Intl\n11h 05m\nGIG\n-\nSCL\n1\n0\n$544\nBasic\nSelect",
          "booking_url_note": "search_link (specific token expired/missing)",
          "sanity": {
            "suspect": false,
            "reasons": [],
            "distance_km": 2934,
            "min_nonstop_minutes": 245
          }
        }
      ]
    }
  },
  "per_leg_airlines": [
    {
      "origin": "SCL",
      "dest": "GIG",
      "date": "2026-06-17",
      "airlines": [
        {
          "airline": "latam",
          "url": "https://www.latamairlines.com/cl/es/ofertas-vuelos?origin=SCL&destination=GIG&outbound=2026-06-17&adt=1&trip=OW"
        },
        {
          "airline": "gol",
          "url": "https://b2c.voegol.com.br/compra/busca-parceiros?pv=br&tipo=OW&de=SCL&para=GIG&ida=2026-06-17&adultos=1"
        },
        {
          "airline": "azul",
          "url": "https://www.voeazul.com.br/br/pt/home/compra/busca?TripType=1&Origin=SCL&Destination=GIG&DepartureDate=2026-06-17&Cabin=Y&Adults=1"
        },
        {
          "airline": "jetsmart",
          "url": "https://jetsmart.com/cl/es/?from=SCL&to=GIG&departure=2026-06-17&adults=1"
        }
      ]
    },
    {
      "origin": "GIG",
      "dest": "SCL",
      "date": "2026-06-29",
      "airlines": [
        {
          "airline": "latam",
          "url": "https://www.latamairlines.com/cl/es/ofertas-vuelos?origin=GIG&destination=SCL&outbound=2026-06-29&adt=1&trip=OW"
        },
        {
          "airline": "gol",
          "url": "https://b2c.voegol.com.br/compra/busca-parceiros?pv=br&tipo=OW&de=GIG&para=SCL&ida=2026-06-29&adultos=1"
        },
        {
          "airline": "azul",
          "url": "https://www.voeazul.com.br/br/pt/home/compra/busca?TripType=1&Origin=GIG&Destination=SCL&DepartureDate=2026-06-29&Cabin=Y&Adults=1"
        },
        {
          "airline": "jetsmart",
          "url": "https://jetsmart.com/cl/es/?from=GIG&to=SCL&departure=2026-06-29&adults=1"
        }
      ]
    }
  ],
  "unique_segments": [
    {
      "origin": "SCL",
      "dest": "GIG",
      "date": "2026-06-17",
      "airline": "",
      "airline_key": "",
      "dep_time": "",
      "arr_time": "",
      "source": "google_flights",
      "url": "",
      "price_value": null,
      "price_currency": "",
      "price_display": "",
      "scrape_status": "no_url",
      "screenshot_path": "",
      "error": ""
    },
    {
      "origin": "SCL",
      "dest": "GIG",
      "date": "2026-06-17",
      "airline": "LATAM Airlines",
      "airline_key": "latam",
      "dep_time": "20:55",
      "arr_time": "02:05",
      "source": "kayak",
      "url": "https://www.latamairlines.com/cl/es/ofertas-vuelos?origin=SCL&destination=GIG&outbound=2026-06-17&adt=1&trip=OW",
      "price_value": null,
      "price_currency": "",
      "price_display": "",
      "scrape_status": "pending",
      "screenshot_path": "",
      "error": ""
    },
    {
      "origin": "GIG",
      "dest": "VIX",
      "date": "2026-06-29",
      "airline": "LATAM Airlines",
      "airline_key": "latam",
      "dep_time": "06:30",
      "arr_time": "",
      "source": "kayak",
      "url": "https://www.latamairlines.com/cl/es/ofertas-vuelos?origin=GIG&destination=VIX&outbound=2026-06-29&adt=1&trip=OW",
      "price_value": null,
      "price_currency": "",
      "price_display": "",
      "scrape_status": "pending",
      "screenshot_path": "",
      "error": ""
    },
    {
      "origin": "VIX",
      "dest": "GRU",
      "date": "2026-06-29",
      "airline": "LATAM Airlines",
      "airline_key": "latam",
      "dep_time": "",
      "arr_time": "",
      "source": "kayak",
      "url": "https://www.latamairlines.com/cl/es/ofertas-vuelos?origin=VIX&destination=GRU&outbound=2026-06-29&adt=1&trip=OW",
      "price_value": null,
      "price_currency": "",
      "price_display": "",
      "scrape_status": "pending",
      "screenshot_path": "",
      "error": ""
    },
    {
      "origin": "GRU",
      "dest": "SCL",
      "date": "2026-06-29",
      "airline": "LATAM Airlines",
      "airline_key": "latam",
      "dep_time": "",
      "arr_time": "18:15",
      "source": "kayak",
      "url": "https://www.latamairlines.com/cl/es/ofertas-vuelos?origin=GRU&destination=SCL&outbound=2026-06-29&adt=1&trip=OW",
      "price_value": null,
      "price_currency": "",
      "price_display": "",
      "scrape_status": "pending",
      "screenshot_path": "",
      "error": ""
    },
    {
      "origin": "GIG",
      "dest": "POA",
      "date": "2026-06-29",
      "airline": "LATAM Airlines",
      "airline_key": "latam",
      "dep_time": "22:15",
      "arr_time": "",
      "source": "kayak",
      "url": "https://www.latamairlines.com/cl/es/ofertas-vuelos?origin=GIG&destination=POA&outbound=2026-06-29&adt=1&trip=OW",
      "price_value": null,
      "price_currency": "",
      "price_display": "",
      "scrape_status": "pending",
      "screenshot_path": "",
      "error": ""
    },
    {
      "origin": "POA",
      "dest": "GRU",
      "date": "2026-06-29",
      "airline": "LATAM Airlines",
      "airline_key": "latam",
      "dep_time": "",
      "arr_time": "",
      "source": "kayak",
      "url": "https://www.latamairlines.com/cl/es/ofertas-vuelos?origin=POA&destination=GRU&outbound=2026-06-29&adt=1&trip=OW",
      "price_value": null,
      "price_currency": "",
      "price_display": "",
      "scrape_status": "pending",
      "screenshot_path": "",
      "error": ""
    },
    {
      "origin": "SCL",
      "dest": "FLN",
      "date": "2026-06-17",
      "airline": "LATAM Airlines",
      "airline_key": "latam",
      "dep_time": "06:00",
      "arr_time": "",
      "source": "kayak",
      "url": "https://www.latamairlines.com/cl/es/ofertas-vuelos?origin=SCL&destination=FLN&outbound=2026-06-17&adt=1&trip=OW",
      "price_value": null,
      "price_currency": "",
      "price_display": "",
      "scrape_status": "pending",
      "screenshot_path": "",
      "error": ""
    },
    {
      "origin": "FLN",
      "dest": "GRU",
      "date": "2026-06-17",
      "airline": "LATAM Airlines",
      "airline_key": "latam",
      "dep_time": "",
      "arr_time": "",
      "source": "kayak",
      "url": "https://www.latamairlines.com/cl/es/ofertas-vuelos?origin=FLN&destination=GRU&outbound=2026-06-17&adt=1&trip=OW",
      "price_value": null,
      "price_currency": "",
      "price_display": "",
      "scrape_status": "pending",
      "screenshot_path": "",
      "error": ""
    },
    {
      "origin": "GRU",
      "dest": "GIG",
      "date": "2026-06-17",
      "airline": "LATAM Airlines",
      "airline_key": "latam",
      "dep_time": "",
      "arr_time": "16:20",
      "source": "kayak",
      "url": "https://www.latamairlines.com/cl/es/ofertas-vuelos?origin=GRU&destination=GIG&outbound=2026-06-17&adt=1&trip=OW",
      "price_value": null,
      "price_currency": "",
      "price_display": "",
      "scrape_status": "pending",
      "screenshot_path": "",
      "error": ""
    }
  ],
  "gf_detail_per_leg": [
    {
      "origin": "SCL",
      "dest": "GIG",
      "date": "2026-06-17",
      "itineraries": [
        {
          "price_value": 202.0,
          "price_currency": "USD",
          "price_display": "202 d\u00f3lares",
          "total_duration_min": 248,
          "n_stops": 0,
          "headline_airline": "",
          "operated_by": "",
          "segments": [
            {
              "origin": "SCL",
              "dest": "GIG",
              "airline": "",
              "airline_key": "",
              "depart_time": "5:57",
              "arrive_time": "11:05",
              "layover_min": 0,
              "operated_by": "",
              "url": "",
              "price_value": null,
              "price_currency": "",
              "price_display": "",
              "price_usd": null,
              "scrape_status": "skipped",
              "error": "",
              "cache_age_s": 0
            }
          ],
          "scraped_total_usd": null,
          "scraped_n_priced": 0,
          "scraped_complete": false
        },
        {
          "price_value": 207.0,
          "price_currency": "USD",
          "price_display": "207 d\u00f3lares",
          "total_duration_min": 250,
          "n_stops": 0,
          "headline_airline": "LATAM",
          "operated_by": "Latam Airlines Group",
          "segments": [
            {
              "origin": "SCL",
              "dest": "GIG",
              "airline": "Latam Airlines Group",
              "airline_key": "latam",
              "depart_time": "20:55",
              "arrive_time": "2:05",
              "layover_min": 0,
              "operated_by": "Latam Airlines Group",
              "url": "https://www.latamairlines.com/cl/es/ofertas-vuelos?origin=SCL&destination=GIG&outbound=2026-06-17&adt=1&trip=OW",
              "price_value": null,
              "price_currency": "",
              "price_display": "",
              "price_usd": null,
              "scrape_status": "skipped",
              "error": "",
              "cache_age_s": 0
            }
          ],
          "scraped_total_usd": null,
          "scraped_n_priced": 0,
          "scraped_complete": false
        },
        {
          "price_value": 230.0,
          "price_currency": "USD",
          "price_display": "230 d\u00f3lares",
          "total_duration_min": 245,
          "n_stops": 0,
          "headline_airline": "LATAM",
          "operated_by": "Latam Airlines Group",
          "segments": [
            {
              "origin": "SCL",
              "dest": "GIG",
              "airline": "Latam Airlines Group",
              "airline_key": "latam",
              "depart_time": "12:20",
              "arrive_time": "17:25",
              "layover_min": 0,
              "operated_by": "Latam Airlines Group",
              "url": "https://www.latamairlines.com/cl/es/ofertas-vuelos?origin=SCL&destination=GIG&outbound=2026-06-17&adt=1&trip=OW",
              "price_value": null,
              "price_currency": "",
              "price_display": "",
              "price_usd": null,
              "scrape_status": "skipped",
              "error": "",
              "cache_age_s": 0
            }
          ],
          "scraped_total_usd": null,
          "scraped_n_priced": 0,
          "scraped_complete": false
        },
        {
          "price_value": 202.0,
          "price_currency": "USD",
          "price_display": "202 d\u00f3lares",
          "total_duration_min": 248,
          "n_stops": 0,
          "headline_airline": "",
          "operated_by": "",
          "segments": [
            {
              "origin": "SCL",
              "dest": "GIG",
              "airline": "",
              "airline_key": "",
              "depart_time": "4:52",
              "arrive_time": "10:00",
              "layover_min": 0,
              "operated_by": "",
              "url": "",
              "price_value": null,
              "price_currency": "",
              "price_display": "",
              "price_usd": null,
              "scrape_status": "skipped",
              "error": "",
              "cache_age_s": 0
            }
          ],
          "scraped_total_usd": null,
          "scraped_n_priced": 0,
          "scraped_complete": false
        },
        {
          "price_value": 208.0,
          "price_currency": "USD",
          "price_display": "208 d\u00f3lares",
          "total_duration_min": 495,
          "n_stops": 1,
          "headline_airline": "LATAM",
          "operated_by": "Latam Airlines Group, Latam Airlines Brasil",
          "segments": [
            {
              "origin": "SCL",
              "dest": "EZE",
              "airline": "Latam Airlines Group",
              "airline_key": "latam",
              "depart_time": "8:30",
              "arrive_time": "",
              "layover_min": 205,
              "operated_by": "Latam Airlines Group",
              "url": "https://www.latamairlines.com/cl/es/ofertas-vuelos?origin=SCL&destination=EZE&outbound=2026-06-17&adt=1&trip=OW",
              "price_value": null,
              "price_currency": "",
              "price_display": "",
              "price_usd": null,
              "scrape_status": "skipped",
              "error": "",
              "cache_age_s": 0
            },
            {
              "origin": "EZE",
              "dest": "GIG",
              "airline": "Latam Airlines Brasil",
              "airline_key": "latam",
              "depart_time": "",
              "arrive_time": "17:45",
              "layover_min": 0,
              "operated_by": "Latam Airlines Brasil",
              "url": "https://www.latamairlines.com/cl/es/ofertas-vuelos?origin=EZE&destination=GIG&outbound=2026-06-17&adt=1&trip=OW",
              "price_value": null,
              "price_currency": "",
              "price_display": "",
              "price_usd": null,
              "scrape_status": "skipped",
              "error": "",
              "cache_age_s": 0
            }
          ],
          "scraped_total_usd": null,
          "scraped_n_priced": 0,
          "scraped_complete": false
        },
        {
          "price_value": 233.0,
          "price_currency": "USD",
          "price_display": "233 d\u00f3lares",
          "total_duration_min": 610,
          "n_stops": 1,
          "headline_airline": "",
          "operated_by": "",
          "segments": [
            {
              "origin": "SCL",
              "dest": "AEP",
              "airline": "",
              "airline_key": "",
              "depart_time": "9:15",
              "arrive_time": "",
              "layover_min": 310,
              "operated_by": "",
              "url": "",
              "price_value": null,
              "price_currency": "",
              "price_display": "",
              "price_usd": null,
              "scrape_status": "skipped",
              "error": "",
              "cache_age_s": 0
            },
            {
              "origin": "AEP",
              "dest": "GIG",
              "airline": "",
              "airline_key": "",
              "depart_time": "",
              "arrive_time": "20:25",
              "layover_min": 0,
              "operated_by": "",
              "url": "",
              "price_value": null,
              "price_currency": "",
              "price_display": "",
              "price_usd": null,
              "scrape_status": "skipped",
              "error": "",
              "cache_age_s": 0
            }
          ],
          "scraped_total_usd": null,
          "scraped_n_priced": 0,
          "scraped_complete": false
        },
        {
          "price_value": 275.0,
          "price_currency": "USD",
          "price_display": "275 d\u00f3lares",
          "total_duration_min": 255,
          "n_stops": 0,
          "headline_airline": "LATAM",
          "operated_by": "Latam Airlines Group",
          "segments": [
            {
              "origin": "SCL",
              "dest": "GIG",
              "airline": "Latam Airlines Group",
              "airline_key": "latam",
              "depart_time": "7:35",
              "arrive_time": "12:50",
              "layover_min": 0,
              "operated_by": "Latam Airlines Group",
              "url": "https://www.latamairlines.com/cl/es/ofertas-vuelos?origin=SCL&destination=GIG&outbound=2026-06-17&adt=1&trip=OW",
              "price_value": null,
              "price_currency": "",
              "price_display": "",
              "price_usd": null,
              "scrape_status": "skipped",
              "error": "",
              "cache_age_s": 0
            }
          ],
          "scraped_total_usd": null,
          "scraped_n_priced": 0,
          "scraped_complete": false
        }
      ],
      "duration_s": 1.2
    },
    {
      "origin": "GIG",
      "dest": "SCL",
      "date": "2026-06-29",
      "itineraries": [
        {
          "price_value": 231.0,
          "price_currency": "USD",
          "price_display": "231 d\u00f3lares",
          "total_duration_min": 776,
          "n_stops": 1,
          "headline_airline": "JetSMART",
          "operated_by": "",
          "segments": [
            {
              "origin": "GIG",
              "dest": "SCL",
              "airline": "JetSMART",
              "airline_key": "jetsmart",
              "depart_time": "19:15",
              "arrive_time": "7:11",
              "layover_min": 0,
              "operated_by": "JetSMART",
              "url": "https://jetsmart.com/cl/es/?from=GIG&to=SCL&departure=2026-06-29&adults=1",
              "price_value": null,
              "price_currency": "",
              "price_display": "",
              "price_usd": null,
              "scrape_status": "skipped",
              "error": "",
              "cache_age_s": 0
            }
          ],
          "scraped_total_usd": null,
          "scraped_n_priced": 0,
          "scraped_complete": false
        },
        {
          "price_value": 340.0,
          "price_currency": "USD",
          "price_display": "340 d\u00f3lares",
          "total_duration_min": 420,
          "n_stops": 1,
          "headline_airline": "LATAM",
          "operated_by": "Latam Airlines Brasil, Latam Airlines Group",
          "segments": [
            {
              "origin": "GIG",
              "dest": "GRU",
              "airline": "Latam Airlines Brasil",
              "airline_key": "latam",
              "depart_time": "12:15",
              "arrive_time": "",
              "layover_min": 90,
              "operated_by": "Latam Airlines Brasil",
              "url": "https://www.latamairlines.com/cl/es/ofertas-vuelos?origin=GIG&destination=GRU&outbound=2026-06-29&adt=1&trip=OW",
              "price_value": null,
              "price_currency": "",
              "price_display": "",
              "price_usd": null,
              "scrape_status": "skipped",
              "error": "",
              "cache_age_s": 0
            },
            {
              "origin": "GRU",
              "dest": "SCL",
              "airline": "Latam Airlines Group",
              "airline_key": "latam",
              "depart_time": "",
              "arrive_time": "18:15",
              "layover_min": 0,
              "operated_by": "Latam Airlines Group",
              "url": "https://www.latamairlines.com/cl/es/ofertas-vuelos?origin=GRU&destination=SCL&outbound=2026-06-29&adt=1&trip=OW",
              "price_value": null,
              "price_currency": "",
              "price_display": "",
              "price_usd": null,
              "scrape_status": "skipped",
              "error": "",
              "cache_age_s": 0
            }
          ],
          "scraped_total_usd": null,
          "scraped_n_priced": 0,
          "scraped_complete": false
        },
        {
          "price_value": 369.0,
          "price_currency": "USD",
          "price_display": "369 d\u00f3lares",
          "total_duration_min": 300,
          "n_stops": 0,
          "headline_airline": "",
          "operated_by": "",
          "segments": [
            {
              "origin": "GIG",
              "dest": "SCL",
              "airline": "",
              "airline_key": "",
              "depart_time": "12:05",
              "arrive_time": "16:05",
              "layover_min": 0,
              "operated_by": "",
              "url": "",
              "price_value": null,
              "price_currency": "",
              "price_display": "",
              "price_usd": null,
              "scrape_status": "skipped",
              "error": "",
              "cache_age_s": 0
            }
          ],
          "scraped_total_usd": null,
          "scraped_n_priced": 0,
          "scraped_complete": false
        },
        {
          "price_value": 249.0,
          "price_currency": "USD",
          "price_display": "249 d\u00f3lares",
          "total_duration_min": 1114,
          "n_stops": 2,
          "headline_airline": "LATAM",
          "operated_by": "Latam Airlines Brasil, Latam Airlines Brasil, Latam Airlines Peru",
          "segments": [
            {
              "origin": "GIG",
              "dest": "GRU",
              "airline": "Latam Airlines Brasil",
              "airline_key": "latam",
              "depart_time": "17:15",
              "arrive_time": "",
              "layover_min": 215,
              "operated_by": "Latam Airlines Brasil",
              "url": "https://www.latamairlines.com/cl/es/ofertas-vuelos?origin=GIG&destination=GRU&outbound=2026-06-29&adt=1&trip=OW",
              "price_value": null,
              "price_currency": "",
              "price_display": "",
              "price_usd": null,
              "scrape_status": "skipped",
              "error": "",
              "cache_age_s": 0
            },
            {
              "origin": "GRU",
              "dest": "SCL",
              "airline": "Latam Airlines Brasil",
              "airline_key": "latam",
              "depart_time": "",
              "arrive_time": "10:49",
              "layover_min": 0,
              "operated_by": "Latam Airlines Brasil",
              "url": "https://www.latamairlines.com/cl/es/ofertas-vuelos?origin=GRU&destination=SCL&outbound=2026-06-29&adt=1&trip=OW",
              "price_value": null,
              "price_currency": "",
              "price_display": "",
              "price_usd": null,
              "scrape_status": "skipped",
              "error": "",
              "cache_age_s": 0
            }
          ],
          "scraped_total_usd": null,
          "scraped_n_priced": 0,
          "scraped_complete": false
        },
        {
          "price_value": 308.0,
          "price_currency": "USD",
          "price_display": "308 d\u00f3lares",
          "total_duration_min": 665,
          "n_stops": 2,
          "headline_airline": "LATAM",
          "operated_by": "Latam Airlines Brasil, Latam Airlines Brasil, Latam Airlines Group",
          "segments": [
            {
              "origin": "GIG",
              "dest": "POA",
              "airline": "Latam Airlines Brasil",
              "airline_key": "latam",
              "depart_time": "11:00",
              "arrive_time": "",
              "layover_min": 70,
              "operated_by": "Latam Airlines Brasil",
              "url": "https://www.latamairlines.com/cl/es/ofertas-vuelos?origin=GIG&destination=POA&outbound=2026-06-29&adt=1&trip=OW",
              "price_value": null,
              "price_currency": "",
              "price_display": "",
              "price_usd": null,
              "scrape_status": "skipped",
              "error": "",
              "cache_age_s": 0
            },
            {
              "origin": "POA",
              "dest": "GRU",
              "airline": "Latam Airlines Brasil",
              "airline_key": "latam",
              "depart_time": "",
              "arrive_time": "",
              "layover_min": 100,
              "operated_by": "Latam Airlines Brasil",
              "url": "https://www.latamairlines.com/cl/es/ofertas-vuelos?origin=POA&destination=GRU&outbound=2026-06-29&adt=1&trip=OW",
              "price_value": null,
              "price_currency": "",
              "price_display": "",
              "price_usd": null,
              "scrape_status": "skipped",
              "error": "",
              "cache_age_s": 0
            },
            {
              "origin": "GRU",
              "dest": "SCL",
              "airline": "Latam Airlines Group",
              "airline_key": "latam",
              "depart_time": "",
              "arrive_time": "21:05",
              "layover_min": 0,
              "operated_by": "Latam Airlines Group",
              "url": "https://www.latamairlines.com/cl/es/ofertas-vuelos?origin=GRU&destination=SCL&outbound=2026-06-29&adt=1&trip=OW",
              "price_value": null,
              "price_currency": "",
              "price_display": "",
              "price_usd": null,
              "scrape_status": "skipped",
              "error": "",
              "cache_age_s": 0
            }
          ],
          "scraped_total_usd": null,
          "scraped_n_priced": 0,
          "scraped_complete": false
        },
        {
          "price_value": 340.0,
          "price_currency": "USD",
          "price_display": "340 d\u00f3lares",
          "total_duration_min": 445,
          "n_stops": 1,
          "headline_airline": "LATAM",
          "operated_by": "Latam Airlines Brasil, Latam Airlines Group",
          "segments": [
            {
              "origin": "GIG",
              "dest": "GRU",
              "airline": "Latam Airlines Brasil",
              "airline_key": "latam",
              "depart_time": "9:00",
              "arrive_time": "",
              "layover_min": 115,
              "operated_by": "Latam Airlines Brasil",
              "url": "https://www.latamairlines.com/cl/es/ofertas-vuelos?origin=GIG&destination=GRU&outbound=2026-06-29&adt=1&trip=OW",
              "price_value": null,
              "price_currency": "",
              "price_display": "",
              "price_usd": null,
              "scrape_status": "skipped",
              "error": "",
              "cache_age_s": 0
            },
            {
              "origin": "GRU",
              "dest": "SCL",
              "airline": "Latam Airlines Group",
              "airline_key": "latam",
              "depart_time": "",
              "arrive_time": "15:25",
              "layover_min": 0,
              "operated_by": "Latam Airlines Group",
              "url": "https://www.latamairlines.com/cl/es/ofertas-vuelos?origin=GRU&destination=SCL&outbound=2026-06-29&adt=1&trip=OW",
              "price_value": null,
              "price_currency": "",
              "price_display": "",
              "price_usd": null,
              "scrape_status": "skipped",
              "error": "",
              "cache_age_s": 0
            }
          ],
          "scraped_total_usd": null,
          "scraped_n_priced": 0,
          "scraped_complete": false
        },
        {
          "price_value": 374.0,
          "price_currency": "USD",
          "price_display": "374 d\u00f3lares",
          "total_duration_min": 795,
          "n_stops": 1,
          "headline_airline": "",
          "operated_by": "",
          "segments": [
            {
              "origin": "GIG",
              "dest": "SCL",
              "airline": "",
              "airline_key": "",
              "depart_time": "20:15",
              "arrive_time": "8:30",
              "layover_min": 0,
              "operated_by": "",
              "url": "",
              "price_value": null,
              "price_currency": "",
              "price_display": "",
              "price_usd": null,
              "scrape_status": "skipped",
              "error": "",
              "cache_age_s": 0
            }
          ],
          "scraped_total_usd": null,
          "scraped_n_priced": 0,
          "scraped_complete": false
        },
        {
          "price_value": 400.0,
          "price_currency": "USD",
          "price_display": "400 d\u00f3lares",
          "total_duration_min": 440,
          "n_stops": 1,
          "headline_airline": "LATAM",
          "operated_by": "Latam Airlines Brasil, Latam Airlines Group",
          "segments": [
            {
              "origin": "GIG",
              "dest": "GRU",
              "airline": "Latam Airlines Brasil",
              "airline_key": "latam",
              "depart_time": "18:40",
              "arrive_time": "",
              "layover_min": 110,
              "operated_by": "Latam Airlines Brasil",
              "url": "https://www.latamairlines.com/cl/es/ofertas-vuelos?origin=GIG&destination=GRU&outbound=2026-06-29&adt=1&trip=OW",
              "price_value": null,
              "price_currency": "",
              "price_display": "",
              "price_usd": null,
              "scrape_status": "skipped",
              "error": "",
              "cache_age_s": 0
            },
            {
              "origin": "GRU",
              "dest": "SCL",
              "airline": "Latam Airlines Group",
              "airline_key": "latam",
              "depart_time": "",
              "arrive_time": "1:00",
              "layover_min": 0,
              "operated_by": "Latam Airlines Group",
              "url": "https://www.latamairlines.com/cl/es/ofertas-vuelos?origin=GRU&destination=SCL&outbound=2026-06-29&adt=1&trip=OW",
              "price_value": null,
              "price_currency": "",
              "price_display": "",
              "price_usd": null,
              "scrape_status": "skipped",
              "error": "",
              "cache_age_s": 0
            }
          ],
          "scraped_total_usd": null,
          "scraped_n_priced": 0,
          "scraped_complete": false
        },
        {
          "price_value": 408.0,
          "price_currency": "USD",
          "price_display": "408 d\u00f3lares",
          "total_duration_min": 480,
          "n_stops": 1,
          "headline_airline": "LATAM",
          "operated_by": "Latam Airlines Brasil, Latam Airlines Group",
          "segments": [
            {
              "origin": "GIG",
              "dest": "AEP",
              "airline": "Latam Airlines Brasil",
              "airline_key": "latam",
              "depart_time": "13:45",
              "arrive_time": "",
              "layover_min": 140,
              "operated_by": "Latam Airlines Brasil",
              "url": "https://www.latamairlines.com/cl/es/ofertas-vuelos?origin=GIG&destination=AEP&outbound=2026-06-29&adt=1&trip=OW",
              "price_value": null,
              "price_currency": "",
              "price_display": "",
              "price_usd": null,
              "scrape_status": "skipped",
              "error": "",
              "cache_age_s": 0
            },
            {
              "origin": "AEP",
              "dest": "SCL",
              "airline": "Latam Airlines Group",
              "airline_key": "latam",
              "depart_time": "",
              "arrive_time": "20:45",
              "layover_min": 0,
              "operated_by": "Latam Airlines Group",
              "url": "https://www.latamairlines.com/cl/es/ofertas-vuelos?origin=AEP&destination=SCL&outbound=2026-06-29&adt=1&trip=OW",
              "price_value": null,
              "price_currency": "",
              "price_display": "",
              "price_usd": null,
              "scrape_status": "skipped",
              "error": "",
              "cache_age_s": 0
            }
          ],
          "scraped_total_usd": null,
          "scraped_n_priced": 0,
          "scraped_complete": false
        },
        {
          "price_value": 414.0,
          "price_currency": "USD",
          "price_display": "414 d\u00f3lares",
          "total_duration_min": 440,
          "n_stops": 1,
          "headline_airline": "LATAM",
          "operated_by": "Latam Airlines Brasil, Latam Airlines Brasil",
          "segments": [
            {
              "origin": "GIG",
              "dest": "GRU",
              "airline": "Latam Airlines Brasil",
              "airline_key": "latam",
              "depart_time": "17:15",
              "arrive_time": "",
              "layover_min": 110,
              "operated_by": "Latam Airlines Brasil",
              "url": "https://www.latamairlines.com/cl/es/ofertas-vuelos?origin=GIG&destination=GRU&outbound=2026-06-29&adt=1&trip=OW",
              "price_value": null,
              "price_currency": "",
              "price_display": "",
              "price_usd": null,
              "scrape_status": "skipped",
              "error": "",
              "cache_age_s": 0
            },
            {
              "origin": "GRU",
              "dest": "SCL",
              "airline": "Latam Airlines Brasil",
              "airline_key": "latam",
              "depart_time": "",
              "arrive_time": "23:35",
              "layover_min": 0,
              "operated_by": "Latam Airlines Brasil",
              "url": "https://www.latamairlines.com/cl/es/ofertas-vuelos?origin=GRU&destination=SCL&outbound=2026-06-29&adt=1&trip=OW",
              "price_value": null,
              "price_currency": "",
              "price_display": "",
              "price_usd": null,
              "scrape_status": "skipped",
              "error": "",
              "cache_age_s": 0
            }
          ],
          "scraped_total_usd": null,
          "scraped_n_priced": 0,
          "scraped_complete": false
        }
      ],
      "duration_s": 1.4
    }
  ]
}